lapa_database_structure/__init__.py
lapa_database_structure/lapa/__init__.py
lapa_database_structure/lapa/authentication/__init__.py
lapa_database_structure/lapa/authentication/enums.py
lapa_database_structure/lapa/authentication/tables.py
lapa_database_structure/lapa/file_storage/__init__.py
lapa_database_structure/lapa/file_storage/tables.py
lapa_database_structure/lapa/public/__init__.py
lapa_database_structure/lapa/public/tables.py
lapa_database_structure/lapa_testing/__init__.py
lapa_database_structure/lapa_testing/authentication/__init__.py
lapa_database_structure/lapa_testing/authentication/enums.py
lapa_database_structure/lapa_testing/authentication/tables.py
lapa_database_structure/lapa_testing/file_storage/__init__.py
lapa_database_structure/lapa_testing/file_storage/tables.py
lapa_database_structure/lapa_testing/public/__init__.py
lapa_database_structure/lapa_testing/public/tables.py
lapa_database_structure-0.0.15.dist-info/METADATA
lapa_database_structure-0.0.15.dist-info/WHEEL
lapa_database_structure-0.0.15.dist-info/top_level.txt
lapa_database_structure-0.0.15.dist-info/RECORD
