Metadata-Version: 2.1
Name: lapa-database-structure
Version: 0.0.15
Summary: database layer for my personal server.
Home-page: https://github.com/B21amish/lapa_database_structure
Author: Amish Palkar, thePmSquare, Lav Sharma, Aaditya Sangishetty
Author-email: amishpalkar302001@gmail.com, thepmsquare@gmail.com, lavsharma2016@gmail.com, adityashetty35@gmail.com
License: UNKNOWN
Platform: UNKNOWN
Classifier: Development Status :: 3 - Alpha
Classifier: Intended Audience :: Developers
Classifier: License :: OSI Approved :: MIT License
Classifier: Programming Language :: Python :: 3
Classifier: Programming Language :: Python :: 3.9
Requires-Dist: sqlalchemy >=2.0.23
